{
  "name": "Halfling (2HD)",
  "type": "monster",
  "img": "systems/fantastic-depths/assets/img/actor/monster1.webp",
  "system": {
    "details": {
      "alignment": "Lawful",
      "size": "S",
      "morale": 8,
      "xpAward": 20,
      "attacks": "1",
      "abilityCount": 0,
      "monsterType": "Demihuman",
      "saveAs": "H2",
      "castAs": "",
      "classAbilityAs": "H2",
      "level": 1,
      "rarity": "Common",
      "weight": ""
    },
    "hp": {
      "hd": "2",
      "value": 9,
      "max": 9
    },
    "na": {
      "wandering": "3d6",
      "lair": "5d8"
    },
    "treasure": "(P+S) B",
    "thac0": {
      "value": 18,
      "mod": {
        "missile": 0,
        "melee": 0
      }
    },
    "movement": {
      "turn": 90,
      "round": 30,
      "day": 18,
      "run": 90,
      "max": 90
    },
    "biography": "<p>Halflings are small, demihuman creatures who often live near their villages. They are skilled with missile weapons, receiving a +1 bonus to attack rolls when using them. Halflings are excellent at hiding, particularly in woods or underbrush, where there is only a 10% chance of being detected while hiding.</p><p>In combat, halflings gain a +2 bonus to Armor Class when fighting larger than man-sized enemies. For every 10 halflings, one will be a leader of level 2, and as long as the leader is alive and fighting alongside them, their morale is 10 rather than 8.</p><p>Halflings typically live in villages, or shires, of 30 to 300 inhabitants. Each village is led by a sheriff (a fighter of level 2-7) and protected by a village guard of 5-20 militia (each with 2 Hit Dice).</p><p><strong>Special Abilities:</strong> Halflings get a +1 bonus to attack rolls when using missile weapons and a +2 bonus to Armor Class when fighting larger creatures.<br><strong>Terrain:</strong> Hill, Open.</p>",
    "wrestling": 13,
    "encumbrance": {
      "max": 1200,
      "value": 0,
      "mv": 0,
      "mv2": 0
    },
    "config": {
      "maxSpellLevel": 0,
      "firstSpellLevel": 1
    },
    "gm": {
      "notes": ""
    },
    "combat": {
      "attacks": 0,
      "isDead": false,
      "deathCount": 0,
      "declaredAction": "attack",
      "attAgainstH": 0,
      "attAgainstM": 0,
      "basicProficiency": true,
      "unskilledToHitMod": -2
    },
    "ac": {
      "naked": 9,
      "nakedAAC": 10,
      "value": 9,
      "total": 9,
      "totalAAC": 10,
      "shield": 0,
      "mod": 0,
      "nakedRanged": 9,
      "nakedRangedAAC": 10,
      "totalRanged": 9,
      "totalRangedAAC": 10,
      "av": "0"
    },
    "thbonus": 1,
    "initiative": {
      "value": 0
    },
    "languages": "",
    "mod": {
      "ac": 0,
      "initiative": 0,
      "combat": {
        "toHit": 0,
        "dmg": "0",
        "toHitRanged": 0,
        "dmgRanged": "0",
        "selfDmg": 0,
        "selfDmgBreath": 0,
        "selfDmgBreathScale": 0,
        "selfDmgMagic": 0,
        "selfDmgFrost": 0,
        "selfDmgFire": 0,
        "selfToHit": 0,
        "selfToHitRanged": 0,
        "selfDmgRanged": 0
      },
      "save": {
        "all": 0,
        "death": 0,
        "wand": 0,
        "paralysis": 0,
        "breath": 0,
        "spell": 0
      },
      "baseAc": 0,
      "upgradeAc": null,
      "upgradeRangedAc": null,
      "rangedAc": 0,
      "wrestling": null,
      "masteryLevelOverride": null
    },
    "acDigest": [],
    "activeLight": null,
    "isEnchanted": false,
    "abilities": {
      "int": {
        "value": 11,
        "total": 11,
        "mod": 0,
        "tempMod": 0
      },
      "con": {
        "value": 10,
        "total": 4,
        "mod": 0,
        "tempMod": 0
      },
      "str": {
        "value": 10,
        "total": 10,
        "mod": 0,
        "tempMod": 0
      },
      "wis": {
        "value": 10,
        "total": 10,
        "mod": 0,
        "tempMod": 0
      },
      "dex": {
        "value": 10,
        "total": 10,
        "mod": 0,
        "tempMod": 0
      },
      "cha": {
        "value": 10,
        "total": 10,
        "mod": 0,
        "loyaltyMod": 0,
        "tempMod": 0
      }
    },
    "monsterTypes": [],
    "tags": [],
    "movement2": {
      "turn": 0,
      "max": 0,
      "round": 0,
      "day": 0,
      "run": 0
    },
    "actorGroups": [
      "weapon-using"
    ]
  },
  "prototypeToken": {
    "name": "Halfling",
    "displayName": 20,
    "actorLink": false,
    "width": 1,
    "height": 1,
    "texture": {
      "src": "systems/fantastic-depths/assets/img/actor/monster1a.webp",
      "scaleX": 1,
      "scaleY": 1,
      "rotation": 0,
      "anchorX": 0.5,
      "anchorY": 0.5,
      "offsetX": 0,
      "offsetY": 0,
      "fit": "contain",
      "tint": "#ffffff",
      "alphaThreshold": 0.75
    },
    "disposition": -1,
    "displayBars": 0,
    "appendNumber": true,
    "prependAdjective": false,
    "lockRotation": false,
    "rotation": 0,
    "alpha": 1,
    "bar1": {
      "attribute": null
    },
    "bar2": {
      "attribute": null
    },
    "light": {
      "negative": false,
      "priority": 0,
      "alpha": 0.5,
      "angle": 360,
      "bright": 0,
      "color": null,
      "coloration": 1,
      "dim": 0,
      "attenuation": 0.5,
      "luminosity": 0.5,
      "saturation": 0,
      "contrast": 0,
      "shadows": 0,
      "animation": {
        "type": null,
        "speed": 5,
        "intensity": 5,
        "reverse": false
      },
      "darkness": {
        "min": 0,
        "max": 1
      }
    },
    "sight": {
      "enabled": true,
      "range": 0,
      "angle": 360,
      "visionMode": "basic",
      "color": null,
      "attenuation": 0,
      "brightness": 0,
      "saturation": -1,
      "contrast": 0
    },
    "detectionModes": [
      {
        "id": "basicSight",
        "enabled": true,
        "range": 60
      }
    ],
    "occludable": {
      "radius": 0
    },
    "ring": {
      "enabled": false,
      "colors": {
        "ring": null,
        "background": null
      },
      "effects": 1,
      "subject": {
        "scale": 1,
        "texture": null
      }
    },
    "flags": {},
    "randomImg": false,
    "turnMarker": {
      "mode": 1,
      "animation": null,
      "src": null,
      "disposition": false
    },
    "movementAction": null
  },
  "items": [
    "s3Um7qXmUAG501Ap",
    "YYYKzXvqkOT6oxOu",
    "XtJrZ4z4q2HizMtH",
    "wOKQgodXv2GboeXf",
    "pgKCZPjGEiPpaXlW",
    "kscxFCaqW4S1HEku",
    "DcoyoppvdNsCNrl5",
    "TFCZeG9ctHJksNx0",
    "5Ymnj5Zixi4qy6r3",
    "0fFrf4mD0vK9tQPo",
    "BBktDXO91XAl8fmr",
    "e0lKV7EAyIl7XM5t",
    "hnmaHR1eoJLu0Jxt",
    "uqmGGpdhi0ydtN5f"
  ],
  "effects": [],
  "folder": "xyIrb6GYNyFjZwEN",
  "ownership": {
    "default": 0,
    "0eyrbleKg5gmY59g": 3
  },
  "flags": {},
  "_stats": {
    "systemId": "fantastic-depths"
  },
  "_id": "HAixVC58xx8ZcMMO",
  "sort": 6800000,
  "_originalKey": "!actors!HAixVC58xx8ZcMMO",
  "embedded": [
    {
      "_originalKey": "!actors.items!HAixVC58xx8ZcMMO.0fFrf4mD0vK9tQPo",
      "name": "Combat Bonuses (H)",
      "type": "specialAbility",
      "img": "systems/fantastic-depths/assets/img/item/specialAbility.png",
      "system": {
        "tags": [],
        "description": "<p>Halflings gain a +1 bonus to all attack rolls when using missile weapons, a +1 bonus to individual initiative, and a -2 AC bonus when attacked by creatures larger than man-sized.</p><p>A creature is considered larger than man-sized if its description includes terms like \"giant,\" \"gargantuan,\" or \"enormous.\" Additionally, real-world creatures that the DM deems larger than a human (such as a horse) also fall into this category. As a general guideline, any non-humanoid creature without a specified size can be assumed to be larger than man-sized if it has 4 or more Hit Dice (HD).</p>",
        "gm": {
          "notes": ""
        },
        "rollFormula": "",
        "operator": "eq",
        "target": "0",
        "rollMode": "publicroll",
        "savingThrow": "",
        "autoSuccess": null,
        "autoFail": null,
        "abilityMod": "",
        "dmgFormula": "",
        "healFormula": "",
        "damageType": "",
        "category": "class",
        "combatManeuver": "null",
        "shortName": "",
        "customSaveCode": "",
        "classKey": "H",
        "showResult": true,
        "quantity": 1,
        "quantityMax": null,
        "conditions": []
      },
      "folder": "GS7EOEGEZk6UwIUu",
      "effects": [
        "USsPJi89yOvhMuPL",
        "m17nznbg8xOnJYvf",
        "ZErQ5xWnSL3z4Gcl"
      ],
      "ownership": {
        "default": 0,
        "0eyrbleKg5gmY59g": 3
      },
      "flags": {},
      "_stats": {
        "systemId": "fantastic-depths"
      },
      "_id": "0fFrf4mD0vK9tQPo",
      "sort": 400000
    },
    {
      "_originalKey": "!actors.items!HAixVC58xx8ZcMMO.5Ymnj5Zixi4qy6r3",
      "folder": "CPCyDDZ2HnUOmFjA",
      "name": "Sword, Short",
      "type": "weapon",
      "_id": "5Ymnj5Zixi4qy6r3",
      "img": "modules/fade-compendiums/assets/img/weapon/shortsword.webp",
      "system": {
        "tags": [],
        "description": "<p>A short sword is a sword with a straight 18” to 2’ blade. Primarily used as a stabbing rather than slashing weapon, this small blade can be used in one hand.</p>",
        "gm": {
          "notes": ""
        },
        "quantity": 1,
        "quantityMax": 0,
        "weight": 30,
        "cost": 7,
        "containerId": "",
        "equipped": true,
        "natural": false,
        "damageRoll": "1d6",
        "damageType": "physical",
        "breath": "",
        "canMelee": true,
        "canRanged": false,
        "savingThrow": "",
        "saveDmgFormula": "",
        "mastery": "Sword, Short",
        "weaponType": "handheld",
        "range": {
          "short": null,
          "medium": null,
          "long": null
        },
        "container": false,
        "equippable": false,
        "totalWeight": 0,
        "totalCost": 0,
        "fuelType": "",
        "ammoType": "",
        "isAmmo": false,
        "mod": {
          "dmg": 0,
          "toHit": 0,
          "dmgRanged": 0,
          "toHitRanged": 0
        },
        "size": "S",
        "grip": "1H",
        "shortName": "",
        "unidentifiedName": "",
        "canSet": false,
        "unidentifiedDesc": "<p>A short sword is a sword with a straight 18” to 2’ blade. Primarily used as a stabbing rather than slashing weapon, this small blade can be used in one hand.</p>",
        "isIdentified": true,
        "isCursed": false,
        "isSlow": false,
        "charges": 0,
        "chargesMax": 0,
        "dmgFormula": null,
        "healFormula": null,
        "isUsable": false,
        "weightEquipped": 30,
        "isOpen": false,
        "isDropped": false,
        "isTreasure": false,
        "damageLabel": "1d6",
        "attacks": {
          "used": 0,
          "max": 1,
          "group": 2
        }
      },
      "effects": [],
      "ownership": {
        "default": 0,
        "0eyrbleKg5gmY59g": 3
      },
      "flags": {},
      "_stats": {
        "systemId": "fantastic-depths"
      },
      "sort": 500000
    },
    {
      "_originalKey": "!actors.items!HAixVC58xx8ZcMMO.BBktDXO91XAl8fmr",
      "name": "Hide, Indoors (H)",
      "type": "specialAbility",
      "img": "systems/fantastic-depths/assets/img/item/specialAbility.png",
      "system": {
        "tags": [],
        "description": "<p data-start=\"478\" data-end=\"814\">Indoors or in dungeons, a Halfling can attempt to hide in deep shadows or cover, but with less success than in natural environments. If sufficient shadows or concealment exist, they have a 33% chance to remain unseen (rolled secretly by the DM). If there is no available cover, the Halfling cannot hide at all.</p><p data-start=\"816\" data-end=\"993\" data-is-last-node=\"\">A bright light, such as a magical light source that eliminates shadows, prevents hiding. A Halfling cannot use this ability while carrying a light source themselves.</p>",
        "gm": {
          "notes": ""
        },
        "rollFormula": "1d100",
        "operator": "lte",
        "target": "0",
        "rollMode": "blindroll",
        "savingThrow": "",
        "autoSuccess": null,
        "autoFail": null,
        "abilityMod": "",
        "dmgFormula": "",
        "healFormula": "",
        "damageType": "",
        "category": "class",
        "combatManeuver": "null",
        "shortName": "",
        "customSaveCode": "",
        "classKey": "H",
        "showResult": true,
        "quantity": 1,
        "quantityMax": null,
        "conditions": []
      },
      "folder": "GS7EOEGEZk6UwIUu",
      "effects": [],
      "ownership": {
        "default": 0,
        "0eyrbleKg5gmY59g": 3
      },
      "flags": {},
      "_stats": {
        "systemId": "fantastic-depths"
      },
      "_id": "BBktDXO91XAl8fmr",
      "sort": 200000
    },
    {
      "_originalKey": "!actors.items!HAixVC58xx8ZcMMO.DcoyoppvdNsCNrl5",
      "folder": "OR1oqiLvw7LWXY42",
      "name": "Dragon Breath",
      "type": "specialAbility",
      "img": "systems/fantastic-depths/assets/img/item/specialAbility.png",
      "_id": "DcoyoppvdNsCNrl5",
      "system": {
        "shortName": "Breath",
        "tags": [],
        "description": "<p>The saving throw against Breath Weapons is used to resist or mitigate the effects of a wide range of powerful exhaled attacks, not limited to dragons. This includes attacks like a dragon’s fiery or icy breath, a gorgon's petrifying breath, or a chimera's elemental breath. Each creature’s breath weapon has specific effects, such as damage, paralysis, or petrification. A successful saving throw generally halves the damage or avoids the secondary effect (such as paralysis or petrification), while failure applies the full consequences. The target number for the saving throw is determined by the character’s class and level.</p>",
        "gm": {
          "notes": ""
        },
        "rollFormula": "1d20",
        "operator": "gte",
        "target": "13",
        "rollMode": "publicroll",
        "savingThrow": "",
        "autoSuccess": null,
        "autoFail": null,
        "abilityMod": "",
        "dmgFormula": "",
        "healFormula": "",
        "damageType": "",
        "category": "save",
        "combatManeuver": "null",
        "customSaveCode": "breath",
        "classKey": null,
        "showResult": true,
        "quantity": 1,
        "quantityMax": null,
        "conditions": []
      },
      "effects": [],
      "sort": 0,
      "ownership": {
        "default": 0,
        "0eyrbleKg5gmY59g": 3
      },
      "flags": {},
      "_stats": {
        "systemId": "fantastic-depths"
      }
    },
    {
      "_originalKey": "!actors.items!HAixVC58xx8ZcMMO.TFCZeG9ctHJksNx0",
      "folder": "OR1oqiLvw7LWXY42",
      "name": "Spells or Magic Staff",
      "type": "specialAbility",
      "img": "systems/fantastic-depths/assets/img/item/specialAbility.png",
      "_id": "TFCZeG9ctHJksNx0",
      "system": {
        "shortName": "Spell",
        "tags": [],
        "description": "<p>The saving throw for Spells or Magic Staff includes resistance against magical effects cast by rods, staves, wands, or through spells. A successful save, rolled on a d20, often reduces or negates the spell's effects entirely. This saving throw is applicable to numerous magical attacks, such as charm spells, fireballs, or paralysis effects, and covers damage, control, or debilitating conditions caused by magical devices or spellcasters. The target number for success is based on the character's class and level.</p>",
        "gm": {
          "notes": ""
        },
        "rollFormula": "1d20",
        "operator": "gte",
        "target": "12",
        "rollMode": "publicroll",
        "savingThrow": "",
        "autoSuccess": null,
        "autoFail": null,
        "abilityMod": "",
        "dmgFormula": "",
        "healFormula": "",
        "damageType": "",
        "category": "save",
        "combatManeuver": "null",
        "customSaveCode": "spell",
        "classKey": null,
        "showResult": true,
        "quantity": 1,
        "quantityMax": null,
        "conditions": []
      },
      "effects": [],
      "sort": 0,
      "ownership": {
        "default": 0,
        "0eyrbleKg5gmY59g": 3
      },
      "flags": {},
      "_stats": {
        "systemId": "fantastic-depths"
      }
    },
    {
      "_originalKey": "!actors.items!HAixVC58xx8ZcMMO.XtJrZ4z4q2HizMtH",
      "folder": "CPCyDDZ2HnUOmFjA",
      "name": "Bow, Short",
      "type": "weapon",
      "_id": "XtJrZ4z4q2HizMtH",
      "img": "icons/weapons/bows/shortbow-leather.webp",
      "system": {
        "tags": [
          "medium",
          "2-handed",
          "slow"
        ],
        "description": "<p>A short bow is a 3’-4’ bow, either made from a single piece of wood or a composite of different woods. A short bow requires both hands to fire. Bows require the use of arrows as ammunition.</p>",
        "gm": {
          "notes": ""
        },
        "quantity": 1,
        "quantityMax": 0,
        "weight": 20,
        "cost": 25,
        "containerId": "",
        "equipped": true,
        "natural": false,
        "damageRoll": "1d6",
        "damageType": "physical",
        "breath": "",
        "canMelee": false,
        "canRanged": true,
        "savingThrow": "",
        "saveDmgFormula": "",
        "mastery": "",
        "weaponType": "monster",
        "range": {
          "short": 50,
          "medium": 100,
          "long": 150
        },
        "container": false,
        "equippable": false,
        "ammoType": "arrow",
        "totalWeight": 0,
        "totalCost": 0,
        "fuelType": "",
        "mod": {
          "dmg": 0,
          "toHit": 0,
          "dmgRanged": 0,
          "toHitRanged": 0
        },
        "isAmmo": false,
        "shortName": "",
        "canSet": false,
        "unidentifiedName": "Bow, Short",
        "unidentifiedDesc": "<p>A short bow is a 3’-4’ bow, either made from a single piece of wood or a composite of different woods. A short bow requires both hands to fire. Bows require the use of arrows as ammunition.</p>",
        "isIdentified": true,
        "isCursed": false,
        "isSlow": false,
        "size": "M",
        "grip": "2H",
        "charges": null,
        "chargesMax": 0,
        "dmgFormula": null,
        "healFormula": null,
        "isUsable": false,
        "attacks": {
          "group": 1,
          "max": 1,
          "used": 0
        },
        "weightEquipped": 20,
        "isOpen": false,
        "isDropped": false,
        "isTreasure": false,
        "damageLabel": "1d6"
      },
      "effects": [],
      "ownership": {
        "default": 0,
        "0eyrbleKg5gmY59g": 3
      },
      "flags": {},
      "_stats": {
        "systemId": "fantastic-depths"
      },
      "sort": 0
    },
    {
      "_originalKey": "!actors.items!HAixVC58xx8ZcMMO.YYYKzXvqkOT6oxOu",
      "folder": "r1PrA7ouTjXcMV7h",
      "name": "Leather Armor",
      "type": "armor",
      "_id": "YYYKzXvqkOT6oxOu",
      "img": "modules/fade-compendiums/assets/img/armor/leather.webp",
      "system": {
        "tags": [],
        "description": "<p>This is a suit primarily composed of leather plates and strips. The leather is often boiled in wax to harden it. Leather armor gives an armor class of 7, and because it is made from natural materials it can be worn by druids. It is also light and quiet enough to be worn by thieves.</p>",
        "gm": {
          "notes": ""
        },
        "quantity": 1,
        "quantityMax": 0,
        "weight": 200,
        "cost": 20,
        "containerId": "",
        "equipped": true,
        "natural": false,
        "ac": 7,
        "isShield": false,
        "totalWeight": 0,
        "totalCost": 0,
        "container": false,
        "equippable": false,
        "dmgFormula": null,
        "armorWeight": "light",
        "mod": 0,
        "totalAC": 9,
        "totalAAC": 9,
        "fuelType": "",
        "ammoType": "",
        "isAmmo": false,
        "shortName": "",
        "unidentifiedName": "",
        "unidentifiedDesc": "<p>This is a suit primarily composed of leather plates and strips. The leather is often boiled in wax to harden it. Leather armor gives an armor class of 7, and because it is made from natural materials it can be worn by druids. It is also light and quiet enough to be worn by thieves.</p>",
        "isIdentified": true,
        "isCursed": false,
        "charges": null,
        "chargesMax": 0,
        "savingThrow": null,
        "healFormula": null,
        "damageType": "",
        "isUsable": false,
        "weightEquipped": 200,
        "isOpen": false,
        "isDropped": false,
        "isTreasure": false,
        "av": null,
        "modRanged": 0,
        "totalRangedAC": 9,
        "totalRangedAAC": 9
      },
      "effects": [],
      "sort": 0,
      "ownership": {
        "default": 0,
        "0eyrbleKg5gmY59g": 3
      },
      "flags": {},
      "_stats": {
        "systemId": "fantastic-depths"
      }
    },
    {
      "_originalKey": "!actors.items!HAixVC58xx8ZcMMO.e0lKV7EAyIl7XM5t",
      "name": "Hide, Natural (H)",
      "type": "specialAbility",
      "img": "systems/fantastic-depths/assets/img/item/specialAbility.png",
      "system": {
        "tags": [],
        "description": "<p>When outdoors, a Halfling can blend into woods, underbrush, or similar natural terrain, making them extremely difficult to spot. If they remain motionless in such cover, they have a 90% chance to remain unseen (rolled secretly by the DM). This ability functions only in natural environments and does not require shadows. If the Halfling moves, they immediately lose the effect and become visible.</p>",
        "gm": {
          "notes": ""
        },
        "rollFormula": "1d100",
        "operator": "lte",
        "target": "0",
        "rollMode": "blindroll",
        "savingThrow": "",
        "autoSuccess": null,
        "autoFail": null,
        "abilityMod": "",
        "dmgFormula": "",
        "healFormula": "",
        "damageType": "",
        "category": "class",
        "combatManeuver": "null",
        "shortName": "",
        "customSaveCode": "",
        "classKey": "H",
        "showResult": true,
        "quantity": 1,
        "quantityMax": null,
        "conditions": []
      },
      "folder": "GS7EOEGEZk6UwIUu",
      "_id": "e0lKV7EAyIl7XM5t",
      "effects": [],
      "ownership": {
        "default": 0,
        "0eyrbleKg5gmY59g": 3
      },
      "flags": {},
      "_stats": {
        "systemId": "fantastic-depths"
      },
      "sort": 100000
    },
    {
      "_originalKey": "!actors.items!HAixVC58xx8ZcMMO.hnmaHR1eoJLu0Jxt",
      "name": "Set Spear vs. Charge",
      "type": "specialAbility",
      "img": "systems/fantastic-depths/assets/img/item/specialAbility.png",
      "system": {
        "tags": [],
        "description": "<p>A character on foot armed with a spear, pike, sword, shield, or lance can set the weapon against a charge. A charge occurs when a monster rushes towards the character, covering at least 20 yards before attacking. This maneuver can also be used against another character's lance attack.</p><p>To \"set vs. charge,\" the character braces the weapon against the ground, pointing it at the approaching enemy. Strength and magic bonuses apply to both the attack and damage rolls. If the attack is successful, the character deals double damage, with adjustments applied after doubling.</p><p>The character must declare the set vs. charge maneuver before entering melee combat with the charging opponent. For example, if the character’s party wins initiative and expects a charge, they can declare this maneuver. Similarly, if charging monsters are spotted several rounds in advance, the character can set their weapon against the charge ahead of time.</p><p>Typically, the attack is made during the monster's movement phase, as soon as it comes within weapon range. If the attack succeeds and kills the monster, it prevents the creature from attacking. If the attack does not kill the monster, it can then attack during its own melee phase of the combat sequence.</p>",
        "gm": {
          "notes": ""
        },
        "rollFormula": "",
        "operator": "eq",
        "target": "0",
        "rollMode": "publicroll",
        "savingThrow": "",
        "autoSuccess": null,
        "autoFail": null,
        "abilityMod": "",
        "dmgFormula": "",
        "healFormula": "",
        "damageType": "",
        "category": "class",
        "combatManeuver": "setSpear",
        "shortName": "",
        "customSaveCode": "",
        "classKey": "F",
        "showResult": true,
        "quantity": 1,
        "quantityMax": null,
        "conditions": []
      },
      "folder": "mNmtATMCAjwUeGOs",
      "_id": "hnmaHR1eoJLu0Jxt",
      "effects": [],
      "ownership": {
        "default": 0,
        "0eyrbleKg5gmY59g": 3
      },
      "flags": {},
      "_stats": {
        "systemId": "fantastic-depths"
      },
      "sort": 0
    },
    {
      "_originalKey": "!actors.items!HAixVC58xx8ZcMMO.kscxFCaqW4S1HEku",
      "folder": "OR1oqiLvw7LWXY42",
      "name": "Turn to Stone or Paralysis",
      "type": "specialAbility",
      "img": "systems/fantastic-depths/assets/img/item/specialAbility.png",
      "_id": "kscxFCaqW4S1HEku",
      "system": {
        "shortName": "Stone",
        "tags": [],
        "description": "<p>The saving throw against \"Stone or Paralysis\" protects a character from attacks or effects that could freeze them in place (paralysis) or turn them into stone. If the saving throw is failed, the character becomes immobilized or petrified, depending on the effect. Paralysis leaves a character aware but unable to act, while petrification turns the character and their carried equipment into a stone statue. The duration or permanence of these effects is specified by the source, and successful saving throws avoid them entirely​​​.</p>",
        "gm": {
          "notes": ""
        },
        "rollFormula": "1d20",
        "operator": "gte",
        "target": "10",
        "rollMode": "publicroll",
        "savingThrow": "",
        "autoSuccess": null,
        "autoFail": null,
        "abilityMod": "",
        "dmgFormula": "",
        "healFormula": "",
        "damageType": "",
        "category": "save",
        "combatManeuver": "null",
        "customSaveCode": "paralysis",
        "classKey": null,
        "showResult": true,
        "quantity": 1,
        "quantityMax": null,
        "conditions": []
      },
      "effects": [],
      "sort": 0,
      "ownership": {
        "default": 0,
        "0eyrbleKg5gmY59g": 3
      },
      "flags": {},
      "_stats": {
        "systemId": "fantastic-depths"
      }
    },
    {
      "_originalKey": "!actors.items!HAixVC58xx8ZcMMO.pgKCZPjGEiPpaXlW",
      "folder": "OR1oqiLvw7LWXY42",
      "name": "Magic Wand",
      "type": "specialAbility",
      "img": "systems/fantastic-depths/assets/img/item/specialAbility.png",
      "_id": "pgKCZPjGEiPpaXlW",
      "system": {
        "tags": [],
        "description": "<p>The Magic Wand saving throw is used to avoid the effects of attacks or abilities activated through magical wands, such as paralysis rays or damage-dealing beams. A successful save, rolled on a d20, indicates that the character avoids or mitigates the harmful effects. The target number to save is determined by the character's class and level, as found on the saving throw table​​.</p>",
        "gm": {
          "notes": ""
        },
        "rollFormula": "1d20",
        "operator": "gte",
        "target": "9",
        "rollMode": "publicroll",
        "savingThrow": "",
        "autoSuccess": null,
        "autoFail": null,
        "abilityMod": "",
        "dmgFormula": "",
        "healFormula": "",
        "damageType": "",
        "category": "save",
        "combatManeuver": "null",
        "customSaveCode": "wand",
        "shortName": "Wand",
        "classKey": null,
        "showResult": true,
        "quantity": 1,
        "quantityMax": null,
        "conditions": []
      },
      "effects": [],
      "sort": 0,
      "ownership": {
        "default": 0,
        "0eyrbleKg5gmY59g": 3
      },
      "flags": {},
      "_stats": {
        "systemId": "fantastic-depths"
      }
    },
    {
      "_originalKey": "!actors.items!HAixVC58xx8ZcMMO.s3Um7qXmUAG501Ap",
      "folder": "CPCyDDZ2HnUOmFjA",
      "name": "Dagger",
      "type": "weapon",
      "_id": "s3Um7qXmUAG501Ap",
      "img": "modules/fade-compendiums/assets/img/weapon/dagger.webp",
      "system": {
        "tags": [
          "magic-user",
          "thrown",
          "small"
        ],
        "description": "<p>A small blade with a one-handed grip. It can be used in melee or thrown as a ranged weapon.</p>",
        "gm": {
          "notes": ""
        },
        "quantity": 1,
        "quantityMax": 1,
        "weight": 10,
        "cost": 3,
        "containerId": "",
        "equipped": true,
        "natural": false,
        "damageRoll": "1d4",
        "damageType": "physical",
        "breath": "",
        "canMelee": true,
        "canRanged": true,
        "savingThrow": "",
        "saveDmgFormula": "",
        "mastery": "",
        "weaponType": "handheld",
        "range": {
          "short": 10,
          "medium": 20,
          "long": 30
        },
        "totalWeight": 0,
        "totalCost": 0,
        "container": false,
        "equippable": false,
        "mod": {
          "dmg": 0,
          "toHit": 0,
          "dmgRanged": 0,
          "toHitRanged": 0
        },
        "fuelType": "",
        "ammoType": "",
        "isAmmo": false,
        "shortName": "",
        "canSet": false,
        "unidentifiedName": "Dagger",
        "unidentifiedDesc": "<p>A small blade with a one-handed grip. It can be used in melee or thrown as a ranged weapon.</p>",
        "isIdentified": true,
        "isCursed": false,
        "isSlow": false,
        "size": "S",
        "grip": "1H",
        "charges": null,
        "chargesMax": 0,
        "dmgFormula": null,
        "healFormula": null,
        "isUsable": false,
        "attacks": {
          "max": 1,
          "used": 0,
          "group": 0
        },
        "weightEquipped": 10,
        "isOpen": false,
        "isDropped": false,
        "isTreasure": false,
        "damageLabel": "1d6"
      },
      "effects": [],
      "sort": 1000000,
      "ownership": {
        "default": 0,
        "0eyrbleKg5gmY59g": 3
      },
      "flags": {},
      "_stats": {
        "systemId": "fantastic-depths"
      }
    },
    {
      "_originalKey": "!actors.items!HAixVC58xx8ZcMMO.uqmGGpdhi0ydtN5f",
      "folder": "u7s4NR16AZdcIm0l",
      "name": "Arrows",
      "type": "ammo",
      "img": "icons/weapons/ammunition/arrows-war-white.webp",
      "_id": "uqmGGpdhi0ydtN5f",
      "system": {
        "shortName": "",
        "description": "<p>Fletched arrows in a quiver. Can be used with a long bow or short bow.</p>",
        "gm": {
          "notes": ""
        },
        "quantity": 20,
        "quantityMax": 20,
        "weight": 0.5,
        "weightEquipped": 0.5,
        "cost": 5,
        "totalWeight": 0,
        "totalCost": 0,
        "containerId": "",
        "equipped": true,
        "equippable": true,
        "ammoType": "arrow",
        "unidentifiedName": "",
        "unidentifiedDesc": "",
        "isIdentified": true,
        "isCursed": false,
        "isDropped": false,
        "savingThrow": "",
        "healFormula": "",
        "damageType": "piercing",
        "isAmmo": true,
        "mod": {
          "dmgRanged": 0,
          "toHitRanged": 0,
          "vsGroup": {},
          "rangeMultiplier": 1
        },
        "charges": 0,
        "chargesMax": 0
      },
      "effects": [],
      "sort": 0,
      "ownership": {
        "default": 0,
        "0eyrbleKg5gmY59g": 3
      },
      "flags": {},
      "_stats": {
        "systemId": "fantastic-depths"
      }
    },
    {
      "_originalKey": "!actors.items!HAixVC58xx8ZcMMO.wOKQgodXv2GboeXf",
      "folder": "OR1oqiLvw7LWXY42",
      "name": "Death Ray or Poison",
      "type": "specialAbility",
      "img": "systems/fantastic-depths/assets/img/item/specialAbility.png",
      "_id": "wOKQgodXv2GboeXf",
      "system": {
        "tags": [],
        "description": "<p>The Death Ray or Poison saving throw is a roll made by a character to resist deadly effects like instant death or paralysis from poisons, spells, or traps. The player rolls a d20 and compares it to their class- and level-specific target number on the saving throw table; success means avoiding or mitigating the harm. A failed roll often results in death (for poison) or other severe consequences, though optional rules may instead inflict substantial damage​​​.</p>",
        "gm": {
          "notes": ""
        },
        "rollFormula": "1d20",
        "operator": "gte",
        "target": "8",
        "rollMode": "publicroll",
        "savingThrow": "",
        "autoSuccess": null,
        "autoFail": null,
        "abilityMod": "",
        "dmgFormula": "",
        "healFormula": "",
        "damageType": "",
        "category": "save",
        "combatManeuver": "null",
        "customSaveCode": "death",
        "shortName": "Death",
        "classKey": null,
        "showResult": true,
        "quantity": 1,
        "quantityMax": null,
        "conditions": []
      },
      "effects": [],
      "sort": 0,
      "ownership": {
        "default": 0,
        "0eyrbleKg5gmY59g": 3
      },
      "flags": {},
      "_stats": {
        "systemId": "fantastic-depths"
      }
    },
    {
      "_originalKey": "!actors.items.effects!HAixVC58xx8ZcMMO.0fFrf4mD0vK9tQPo.USsPJi89yOvhMuPL",
      "name": "Initiative Bonus",
      "img": "icons/svg/aura.svg",
      "origin": "Compendium.fade-compendiums.item-compendium.Item.ZfID3ksMSPpUiGFM",
      "duration": {
        "rounds": null,
        "startTime": 4644910,
        "seconds": null,
        "combat": null,
        "turns": null,
        "startRound": null,
        "startTurn": null
      },
      "disabled": false,
      "_id": "USsPJi89yOvhMuPL",
      "type": "base",
      "system": {},
      "changes": [
        {
          "key": "system.mod.initiative",
          "mode": 2,
          "value": "1",
          "priority": null
        }
      ],
      "description": "",
      "tint": "#ffffff",
      "transfer": true,
      "statuses": [],
      "sort": 0,
      "flags": {},
      "_stats": {
        "systemId": "fantastic-depths"
      }
    },
    {
      "_originalKey": "!actors.items.effects!HAixVC58xx8ZcMMO.0fFrf4mD0vK9tQPo.ZErQ5xWnSL3z4Gcl",
      "name": "+1 Missile Attack",
      "img": "icons/svg/aura.svg",
      "origin": "Compendium.fade-compendiums.item-compendium.Item.j1FIuV7aJhu48YOk",
      "duration": {
        "rounds": null,
        "startTime": 4644910,
        "seconds": null,
        "combat": null,
        "turns": null,
        "startRound": null,
        "startTurn": null
      },
      "disabled": false,
      "_id": "ZErQ5xWnSL3z4Gcl",
      "type": "base",
      "system": {},
      "changes": [
        {
          "key": "system.mod.combat.toHitRanged",
          "mode": 2,
          "value": "1",
          "priority": null
        }
      ],
      "description": "",
      "tint": "#ffffff",
      "transfer": true,
      "statuses": [],
      "sort": 0,
      "flags": {},
      "_stats": {
        "systemId": "fantastic-depths"
      }
    },
    {
      "_originalKey": "!actors.items.effects!HAixVC58xx8ZcMMO.0fFrf4mD0vK9tQPo.m17nznbg8xOnJYvf",
      "name": "AC +1 vs Large",
      "img": "icons/svg/aura.svg",
      "origin": "Compendium.fade-compendiums.item-compendium.Item.j1FIuV7aJhu48YOk",
      "duration": {
        "rounds": null,
        "startTime": 4644910,
        "seconds": null,
        "combat": null,
        "turns": null,
        "startRound": null,
        "startTurn": null
      },
      "disabled": false,
      "_id": "m17nznbg8xOnJYvf",
      "type": "base",
      "system": {},
      "changes": [
        {
          "key": "system.mod.acVsLarge",
          "mode": 2,
          "value": "2",
          "priority": null
        }
      ],
      "description": "",
      "tint": "#ffffff",
      "transfer": true,
      "statuses": [],
      "sort": 0,
      "flags": {},
      "_stats": {
        "systemId": "fantastic-depths"
      }
    }
  ]
}