{
  "folder": "SOm66tqvBRVOnUR6",
  "name": "Hit Location - Arachnid",
  "_id": "qAB9xn8VbRbICIIc",
  "img": "icons/creatures/invertebrates/spider-pink-purple.webp",
  "description": "",
  "results": [
    "4iaUc2i6O3CQVYxt",
    "1bOMTiPpLxFVYnJG",
    "c5ejs7JdZ8jwSsA8",
    "6WnsPGIDtthweIfC",
    "Etv0RNZNudj1WOr4",
    "9FNxmel4k2QKDaa4",
    "2hBnMZ6b9l8ahncn",
    "IJQyzYWGWqtEvOEv",
    "wK2nm0xPbb7Y8h9b",
    "b025qdLKOmYkxWhe"
  ],
  "replacement": true,
  "displayRoll": true,
  "ownership": {
    "default": 0,
    "0eyrbleKg5gmY59g": 3
  },
  "flags": {
    "core": {},
    "exportSource": {
      "world": "dandd-1e",
      "system": "gs-fantastic-depths",
      "coreVersion": "11.315",
      "systemVersion": "1.11.5"
    }
  },
  "_stats": {
    "compendiumSource": "Compendium.fade-compendiums.roll-table-compendium.RollTable.qAB9xn8VbRbICIIc",
    "duplicateSource": null,
    "coreVersion": "12.331",
    "systemId": "fantastic-depths",
    "systemVersion": "0.7.22-rc.4",
    "createdTime": 1739749686178,
    "modifiedTime": 1739749686178,
    "lastModifiedBy": "0eyrbleKg5gmY59g"
  },
  "formula": "1d20",
  "sort": 0,
  "_originalKey": "!tables!qAB9xn8VbRbICIIc",
  "embedded": [
    {
      "_originalKey": "!tables.results!qAB9xn8VbRbICIIc.1bOMTiPpLxFVYnJG",
      "type": "text",
      "weight": 1,
      "range": [
        3,
        4
      ],
      "drawn": false,
      "_id": "1bOMTiPpLxFVYnJG",
      "text": "Left Rear Leg",
      "documentId": null,
      "flags": {},
      "img": "icons/svg/d20-black.svg",
      "_stats": {}
    },
    {
      "_originalKey": "!tables.results!qAB9xn8VbRbICIIc.2hBnMZ6b9l8ahncn",
      "type": "text",
      "weight": 1,
      "range": [
        13,
        14
      ],
      "drawn": false,
      "_id": "2hBnMZ6b9l8ahncn",
      "text": "Abdomen",
      "documentId": null,
      "flags": {},
      "img": "icons/svg/d20-black.svg",
      "_stats": {}
    },
    {
      "_originalKey": "!tables.results!qAB9xn8VbRbICIIc.4iaUc2i6O3CQVYxt",
      "type": "text",
      "weight": 1,
      "range": [
        1,
        2
      ],
      "drawn": false,
      "_id": "4iaUc2i6O3CQVYxt",
      "text": "Right Rear Leg",
      "documentId": null,
      "flags": {},
      "img": "icons/svg/d20-black.svg",
      "_stats": {}
    },
    {
      "_originalKey": "!tables.results!qAB9xn8VbRbICIIc.6WnsPGIDtthweIfC",
      "type": "text",
      "weight": 1,
      "range": [
        7,
        8
      ],
      "drawn": false,
      "_id": "6WnsPGIDtthweIfC",
      "text": "Mid Left Leg",
      "documentId": null,
      "flags": {},
      "img": "icons/svg/d20-black.svg",
      "_stats": {}
    },
    {
      "_originalKey": "!tables.results!qAB9xn8VbRbICIIc.9FNxmel4k2QKDaa4",
      "type": "text",
      "weight": 1,
      "range": [
        11,
        12
      ],
      "drawn": false,
      "_id": "9FNxmel4k2QKDaa4",
      "text": "Fore Left Leg",
      "documentId": null,
      "flags": {},
      "img": "icons/svg/d20-black.svg",
      "_stats": {}
    },
    {
      "_originalKey": "!tables.results!qAB9xn8VbRbICIIc.Etv0RNZNudj1WOr4",
      "type": "text",
      "weight": 1,
      "range": [
        9,
        10
      ],
      "drawn": false,
      "_id": "Etv0RNZNudj1WOr4",
      "text": "Fore Right Leg",
      "documentId": null,
      "flags": {},
      "img": "icons/svg/d20-black.svg",
      "_stats": {}
    },
    {
      "_originalKey": "!tables.results!qAB9xn8VbRbICIIc.IJQyzYWGWqtEvOEv",
      "type": "text",
      "weight": 1,
      "range": [
        15,
        16
      ],
      "drawn": false,
      "_id": "IJQyzYWGWqtEvOEv",
      "text": "Front Right Leg",
      "documentId": null,
      "flags": {},
      "img": "icons/svg/d20-black.svg",
      "_stats": {}
    },
    {
      "_originalKey": "!tables.results!qAB9xn8VbRbICIIc.b025qdLKOmYkxWhe",
      "type": "text",
      "weight": 1,
      "range": [
        19,
        20
      ],
      "drawn": false,
      "_id": "b025qdLKOmYkxWhe",
      "text": "Cephalothorax",
      "documentId": null,
      "flags": {},
      "img": "icons/svg/d20-black.svg",
      "_stats": {}
    },
    {
      "_originalKey": "!tables.results!qAB9xn8VbRbICIIc.c5ejs7JdZ8jwSsA8",
      "type": "text",
      "weight": 1,
      "range": [
        5,
        6
      ],
      "drawn": false,
      "_id": "c5ejs7JdZ8jwSsA8",
      "text": "Mid Right Leg",
      "documentId": null,
      "flags": {},
      "img": "icons/svg/d20-black.svg",
      "_stats": {}
    },
    {
      "_originalKey": "!tables.results!qAB9xn8VbRbICIIc.wK2nm0xPbb7Y8h9b",
      "type": "text",
      "weight": 1,
      "range": [
        17,
        18
      ],
      "drawn": false,
      "_id": "wK2nm0xPbb7Y8h9b",
      "text": "Front Left Leg",
      "documentId": null,
      "flags": {},
      "img": "icons/svg/d20-black.svg",
      "_stats": {}
    }
  ]
}